src/mealy_toggle.v
`timescale 1ns/1ps

module mealy_toggle (
    input wire clk, rst, enable, bit_in,
    output reg state,
    output wire [1:0] value
);

    always @(posedge clk) begin
        if (rst) state <= 1'b0;
        else if (enable && bit_in) state <= ~state;
    end

    // Reset changes state at the rising edge; value is combinational.
    assign value = !bit_in ? 2'b00 : (state ? 2'b01 : 2'b10);

endmodule

sim/tb_mealy_toggle.sv
`timescale 1ns/1ps

module tb_mealy_toggle;

reg clk = 0, rst = 1;
integer checks = 0;

always #5 clk = ~clk;

task step; begin @(posedge clk); #1; end endtask

task check(input condition, input [8*100-1:0] description);
begin
    checks = checks + 1;
    if (condition !== 1'b1) begin
        $display("LAB2_FAIL %0s time=%0t", description, $time);
        $fatal(1, "check failed");
    end
end
endtask

task finish;
begin
    $display("LAB2_PASS mealy_toggle checks=%0d", checks);
    $finish;
end
endtask

initial begin $dumpfile("wave.vcd"); $dumpvars(0, tb_mealy_toggle); end
initial begin #100000; $fatal(1, "watchdog timeout"); end

reg enable = 0, bit_in = 0;
wire state;
wire [1:0] value;

mealy_toggle dut(clk, rst, enable, bit_in, state, value);

initial begin
    step; check({state, value} === 3'b000, "reset input zero"); rst = 0;
    bit_in = 1; #1; check({state, value} === 3'b010, "S0 input changes between clocks");
    step; check({state, value} === 3'b010, "disabled state still has Mealy output");
    enable = 1; step; check({state, value} === 3'b101, "transition to S1");
    bit_in = 0; #1; check({state, value} === 3'b100, "S1 input zero immediately");
    step; check(state === 1, "input zero holds S1");
    bit_in = 1; #1; check(value === 1, "S1 pre-edge value");
    step; check({state, value} === 3'b010, "transition to S0");
    step; check(state === 1, "toggle again");
    rst = 1; step; check({state, value} === 3'b010, "reset state with input one");
    bit_in = 0; #1; check(value === 0, "clear combinational output");
    finish;
end

endmodule

evidence/07/vscode/wave.vcd
$date
	Wed Sep 16 18:35:40 2026
$end
$version
	Icarus Verilog
$end
$timescale
	1ps
$end
$scope module tb_mealy_toggle $end
$var wire 2 ! value [1:0] $end
$var wire 1 " state $end
$var reg 1 # bit_in $end
$var reg 1 $ clk $end
$var reg 1 % enable $end
$var reg 1 & rst $end
$var integer 32 ' checks [31:0] $end
$scope module dut $end
$var wire 1 # bit_in $end
$var wire 1 $ clk $end
$var wire 1 % enable $end
$var wire 1 & rst $end
$var wire 2 ( value [1:0] $end
$var reg 1 " state $end
$upscope $end
$scope task check $end
$var reg 1 ) condition $end
$var reg 800 * description [799:0] $end
$upscope $end
$scope task finish $end
$upscope $end
$scope task step $end
$upscope $end
$upscope $end
$enddefinitions $end
$comment Show the parameter values. $end
$dumpall
$end
#0
$dumpvars
bx *
x)
b0 (
b0 '
1&
0%
0$
0#
x"
b0 !
$end
#5000
0"
1$
#6000
b10 !
b10 (
1#
0&
b1 '
b1110010011001010111001101100101011101000010000001101001011011100111000001110101011101000010000001111010011001010111001001101111 *
1)
#7000
b10 '
b1010011001100000010000001101001011011100111000001110101011101000010000001100011011010000110000101101110011001110110010101110011001000000110001001100101011101000111011101100101011001010110111000100000011000110110110001101111011000110110101101110011 *
#10000
0$
#15000
1$
#16000
1%
b11 '
b1100100011010010111001101100001011000100110110001100101011001000010000001110011011101000110000101110100011001010010000001110011011101000110100101101100011011000010000001101000011000010111001100100000010011010110010101100001011011000111100100100000011011110111010101110100011100000111010101110100 *
#20000
0$
#25000
b1 !
b1 (
1"
1$
#26000
b0 !
b0 (
0#
b100 '
b1110100011100100110000101101110011100110110100101110100011010010110111101101110001000000111010001101111001000000101001100110001 *
#27000
b101 '
b1010011001100010010000001101001011011100111000001110101011101000010000001111010011001010111001001101111001000000110100101101101011011010110010101100100011010010110000101110100011001010110110001111001 *
#30000
0$
#35000
1$
#36000
b1 !
b1 (
1#
b110 '
b1101001011011100111000001110101011101000010000001111010011001010111001001101111001000000110100001101111011011000110010001110011001000000101001100110001 *
#37000
b111 '
b101001100110001001000000111000001110010011001010010110101100101011001000110011101100101001000000111011001100001011011000111010101100101 *
#40000
0$
#45000
b10 !
b10 (
0"
1$
#46000
b1000 '
b1110100011100100110000101101110011100110110100101110100011010010110111101101110001000000111010001101111001000000101001100110000 *
#50000
0$
#55000
b1 !
b1 (
1"
1$
#56000
1&
b1001 '
b11101000110111101100111011001110110110001100101001000000110000101100111011000010110100101101110 *
#60000
0$
#65000
b10 !
b10 (
0"
1$
#66000
b0 !
b0 (
0#
b1010 '
b111001001100101011100110110010101110100001000000111001101110100011000010111010001100101001000000111011101101001011101000110100000100000011010010110111001110000011101010111010000100000011011110110111001100101 *
#67000
b1011 '
b110001101101100011001010110000101110010001000000110001101101111011011010110001001101001011011100110000101110100011010010110111101101110011000010110110000100000011011110111010101110100011100000111010101110100 *
